LICENSE
MANIFEST.in
README.rst
setup.cfg
setup.py
groio/__init__.py
groio/groio.py
groio.egg-info/PKG-INFO
groio.egg-info/SOURCES.txt
groio.egg-info/dependency_links.txt
groio.egg-info/top_level.txt
tests/test_resources/fail.gro
tests/test_resources/fail_100000.gro
tests/test_resources/missing_total_atoms.gro
tests/test_resources/regular.gro
tests/test_resources/write.gro